neolegoff_bank/__init__.py
neolegoff_bank/exceptions/__init__.py
neolegoff_bank/models/__init__.py
neolegoff_bank/models/api_response_base.py
neolegoff_bank/models/neolegoff_app_data.py
neolegoff_bank-0.0.1a3.dist-info/LICENSE
neolegoff_bank-0.0.1a3.dist-info/METADATA
neolegoff_bank-0.0.1a3.dist-info/WHEEL
neolegoff_bank-0.0.1a3.dist-info/top_level.txt
neolegoff_bank-0.0.1a3.dist-info/RECORD
