Metadata-Version: 2.1
Name: neolegoff-bank
Version: 0.0.1a3
Summary: Simple Tinkoff Bank API client
Home-page: https://github.com/WhiteApfel/neolegoff_bank
Author: WhiteApfel
Author-email: white@pfel.ru
License: Mozilla Public License 2.0
Project-URL: Source code, https://github.com/WhiteApfel/neolegoff_bank
Project-URL: Write me, https://t.me/whiteapfel
Keywords: tinkoff api bank
License-File: LICENSE
Requires-Dist: httpx (==0.23.3)
Requires-Dist: pydantic (==1.10.5)
Requires-Dist: appdirs (~=1.4.4)
Requires-Dist: randmac (~=0.1)
Requires-Dist: pycryptodomex (==3.17)
